Metadata-Version: 2.1
Name: odoo-addon-base_import_security_group
Version: 18.0.1.0.0.4
Requires-Python: >=3.10
Requires-Dist: odoo==18.0.*
Summary: Group-based permissions for importing CSV files
Home-page: https://github.com/OCA/server-ux
License: AGPL-3
Author: Odoo Community Association (OCA), Alejandro Santana <alejandrosantana@anubia.es>, Onestein
Author-email: support@odoo-community.org
Classifier: Programming Language :: Python
Classifier: Framework :: Odoo
Classifier: Framework :: Odoo :: 18.0
Classifier: License :: OSI Approved :: GNU Affero General Public License v3
